lopq/__init__.py
lopq/eval.py
lopq/lopq_model_pb2.py
lopq/model.py
lopq/package_metadata.json
lopq/search.py
lopq/utils.py
lopq-1.0.26.dist-info/DESCRIPTION.rst
lopq-1.0.26.dist-info/METADATA
lopq-1.0.26.dist-info/RECORD
lopq-1.0.26.dist-info/WHEEL
lopq-1.0.26.dist-info/metadata.json
lopq-1.0.26.dist-info/top_level.txt
