Metadata-Version: 2.0
Name: lopq
Version: 1.0.26
Summary: Python code for training and deploying Locally Optimized Product Quantization (LOPQ) for approximate nearest neighbor search of high dimensional data.
Home-page: http://github.com/yahoo/lopq
Author: Clayton Mellina,Yannis Kalantidis,Huy Nguyen
Author-email: clayton@yahoo-inc.com
License: Apache-2.0
Keywords: lopq,locally optimized product quantization,product quantization,compression,ann,approximate nearest neighbor,similarity search
Platform: Windows
Platform: Linux
Platform: Solaris
Platform: Mac OS-X
Platform: Unix
Classifier: Development Status :: 5 - Production/Stable
Classifier: License :: OSI Approved :: Apache Software License
Classifier: Intended Audience :: Developers
Classifier: Intended Audience :: Science/Research
Classifier: Natural Language :: English
Classifier: Operating System :: MacOS :: MacOS X
Classifier: Operating System :: Microsoft :: Windows
Classifier: Operating System :: POSIX
Classifier: Operating System :: POSIX
Classifier: Operating System :: Unix
Classifier: Programming Language :: Python :: 2.7
Classifier: Topic :: Scientific/Engineering
Classifier: Topic :: Software Development
Requires-Dist: lmdb (>=0.87)
Requires-Dist: numpy (>=1.10)
Requires-Dist: protobuf (>=2.6)
Requires-Dist: scikit-learn (>=0.15)
Requires-Dist: scipy (>=0.15)
